primer_analyze_client/__init__.py
primer_analyze_client/__version__.py
primer_analyze_client/analyze_client.py
primer_analyze_client-0.0.4.dist-info/METADATA
primer_analyze_client-0.0.4.dist-info/WHEEL
primer_analyze_client-0.0.4.dist-info/top_level.txt
primer_analyze_client-0.0.4.dist-info/RECORD
